lanforge_client/__init__.py
lanforge_client/lanforge_api.py
lanforge_client/logg.py
lanforge_client/strutil.py
lanforge_scripts/__init__.py
lanforge_scripts/ap_ctl.py
lanforge_scripts/auto_install_gui.py
lanforge_scripts/connectTest.py
lanforge_scripts/cpu_stats.py
lanforge_scripts/emailHelper.py
lanforge_scripts/lf_mail.py
lanforge_scripts/lf_sniff.py
lanforge_scripts/lf_tos_plus_test.py
lanforge_scripts/lf_tos_test.py
lanforge_scripts/lf_tx_power.py
lanforge_scripts/openwrt_ctl.py
lanforge_scripts/pulse_detect.py
lanforge_scripts/stationStressTest.py
lanforge_scripts/tos_plus_auto.py
lanforge_scripts/wifi_ctl_9800_3504.py
lanforge_scripts/py_dashboard/GhostRequest.py
lanforge_scripts/py_dashboard/GrafanaRequest.py
lanforge_scripts/py_dashboard/InfluxRequest.py
lanforge_scripts/py_dashboard/__init__.py
lanforge_scripts/py_json/__init__.py
lanforge_scripts/py_json/create_wanlink.py
lanforge_scripts/py_json/cv_dut_profile.py
lanforge_scripts/py_json/cv_test_manager.py
lanforge_scripts/py_json/cv_test_reports.py
lanforge_scripts/py_json/dataplane_test_profile.py
lanforge_scripts/py_json/dut_profile.py
lanforge_scripts/py_json/fio_endp_profile.py
lanforge_scripts/py_json/gen_cxprofile.py
lanforge_scripts/py_json/http_profile.py
lanforge_scripts/py_json/l3_cxprofile.py
lanforge_scripts/py_json/l4_cxprofile.py
lanforge_scripts/py_json/lf_attenmod.py
lanforge_scripts/py_json/lf_cv_base.py
lanforge_scripts/py_json/lfdata.py
lanforge_scripts/py_json/mac_vlan_profile.py
lanforge_scripts/py_json/multicast_profile.py
lanforge_scripts/py_json/port_probe.py
lanforge_scripts/py_json/port_utils.py
lanforge_scripts/py_json/qvlan_profile.py
lanforge_scripts/py_json/realm.py
lanforge_scripts/py_json/realm_test.py
lanforge_scripts/py_json/show_ports.py
lanforge_scripts/py_json/station_profile.py
lanforge_scripts/py_json/test_base.py
lanforge_scripts/py_json/test_group_profile.py
lanforge_scripts/py_json/test_histogram.py
lanforge_scripts/py_json/test_utility.py
lanforge_scripts-0.0.13.dist-info/METADATA
lanforge_scripts-0.0.13.dist-info/WHEEL
lanforge_scripts-0.0.13.dist-info/license.txt
lanforge_scripts-0.0.13.dist-info/top_level.txt
lanforge_scripts-0.0.13.dist-info/RECORD
