Metadata-Version: 2.1
Name: lanforge-scripts
Version: 0.0.13
Summary: Automate LANforge devices
Home-page: https://github.com/greearb/lanforge-scripts
Author: Candela Technologies
License: BSD 3-clause license
Project-URL: Homepage, https://www.candelatech.com
Platform: UNKNOWN
Classifier: Programming Language :: Python :: 3
Classifier: Operating System :: OS Independent
Requires-Python: >=3.7, <4
License-File: license.txt
Requires-Dist: pandas
Requires-Dist: plotly
Requires-Dist: numpy
Requires-Dist: cryptography
Requires-Dist: paramiko
Requires-Dist: bokeh
Requires-Dist: pyarrow
Requires-Dist: websocket-client
Requires-Dist: xlsxwriter
Requires-Dist: pyshark
Requires-Dist: influxdb
Requires-Dist: influxdb-client
Requires-Dist: matplotlib
Requires-Dist: pdfkit
Requires-Dist: pip-search
Requires-Dist: pyserial
Requires-Dist: pexpect-serial
Requires-Dist: scp
Requires-Dist: dash
Requires-Dist: pyjwt
